rcs/__init__.py
rcs/audiences/__init__.py
rcs/audiences/client.py
rcs/audiences/contacts/__init__.py
rcs/audiences/contacts/client.py
rcs/audiences/contacts/raw_client.py
rcs/audiences/raw_client.py
rcs/audiences/types/__init__.py
rcs/audiences/types/audiences_get_response.py
rcs/base_client.py
rcs/brands/__init__.py
rcs/brands/client.py
rcs/brands/raw_client.py
rcs/brands/types/__init__.py
rcs/brands/types/autofill_brand_options.py
rcs/brands/types/upsert_brand_schema_contact.py
rcs/brands/types/upsert_brand_schema_entity_type.py
rcs/brands/types/upsert_brand_schema_sector.py
rcs/brands/types/upsert_brand_schema_type.py
rcs/campaigns/__init__.py
rcs/campaigns/client.py
rcs/campaigns/dlc/__init__.py
rcs/campaigns/dlc/client.py
rcs/campaigns/dlc/raw_client.py
rcs/campaigns/dlc/types/__init__.py
rcs/campaigns/dlc/types/dlc_campaign_help_keywords.py
rcs/campaigns/dlc/types/dlc_campaign_keywords.py
rcs/campaigns/dlc/types/dlc_campaign_links.py
rcs/campaigns/dlc/types/dlc_campaign_opt_in_keywords.py
rcs/campaigns/dlc/types/dlc_campaign_opt_out_keywords.py
rcs/campaigns/dlc/types/dlc_campaign_options.py
rcs/campaigns/dlc/types/dlc_campaign_use_case.py
rcs/campaigns/raw_client.py
rcs/campaigns/rcs/__init__.py
rcs/campaigns/rcs/client.py
rcs/campaigns/rcs/raw_client.py
rcs/campaigns/rcs/types/__init__.py
rcs/campaigns/rcs/types/rcs_agent.py
rcs/campaigns/rcs/types/rcs_agent_email.py
rcs/campaigns/rcs/types/rcs_agent_phone.py
rcs/campaigns/rcs/types/rcs_agent_website.py
rcs/campaigns/rcs/types/rcs_autofill_response.py
rcs/campaigns/rcs/types/rcs_campaign_help_keywords.py
rcs/campaigns/rcs/types/rcs_campaign_keywords.py
rcs/campaigns/rcs/types/rcs_campaign_opt_in_keywords.py
rcs/campaigns/rcs/types/rcs_campaign_opt_out_keywords.py
rcs/campaigns/rcs/types/rcs_campaign_traffic.py
rcs/campaigns/rcs/types/rcs_links.py
rcs/campaigns/rcs/types/rcs_use_case.py
rcs/campaigns/toll_free/__init__.py
rcs/campaigns/toll_free/client.py
rcs/campaigns/toll_free/raw_client.py
rcs-2.0.14.dist-info/METADATA
rcs-2.0.14.dist-info/WHEEL
rcs-2.0.14.dist-info/RECORD
